{
 "_type": "album",
 "api_path": "/albums/121108",
 "cover_art_thumbnail_url": "https://images.genius.com/feca78e7614ab073a693106d2689112e.300x300x1.png",
 "cover_art_url": "https://images.genius.com/feca78e7614ab073a693106d2689112e.1000x1000x1.png",
 "full_title": "Eyes Wide Open  by Sabrina Carpenter",
 "id": 121108,
 "name": "Eyes Wide Open ",
 "name_with_artist": "Eyes Wide Open  (artist: Sabrina Carpenter)",
 "primary_artist_names": "Sabrina Carpenter",
 "release_date_components": {
  "year": 2015,
  "month": 4,
  "day": 14
 },
 "release_date_for_display": "April 14, 2015",
 "url": "https://genius.com/albums/Sabrina-carpenter/Eyes-wide-open",
 "artist": {
  "_type": "artist",
  "api_path": "/artists/249592",
  "header_image_url": "https://images.genius.com/3d8df19075a7d820abc18af8b160de93.1000x333x1.jpg",
  "id": 249592,
  "image_url": "https://images.genius.com/ba5ff0975b4976a9351f3f26e66fa4b9.965x965x1.jpg",
  "index_character": "s",
  "is_meme_verified": false,
  "is_verified": true,
  "name": "Sabrina Carpenter",
  "slug": "Sabrina-carpenter",
  "url": "https://genius.com/artists/Sabrina-carpenter",
  "iq": 2353
 },
 "primary_artists": [
  {
   "_type": "artist",
   "api_path": "/artists/249592",
   "header_image_url": "https://images.genius.com/3d8df19075a7d820abc18af8b160de93.1000x333x1.jpg",
   "id": 249592,
   "image_url": "https://images.genius.com/ba5ff0975b4976a9351f3f26e66fa4b9.965x965x1.jpg",
   "index_character": "s",
   "is_meme_verified": false,
   "is_verified": true,
   "name": "Sabrina Carpenter",
   "slug": "Sabrina-carpenter",
   "url": "https://genius.com/artists/Sabrina-carpenter",
   "iq": 2353
  }
 ],
 "tracks": [
  {
   "number": 1,
   "song": {
    "_type": "song",
    "annotation_count": 5,
    "api_path": "/songs/744882",
    "artist_names": "Sabrina Carpenter",
    "full_title": "Eyes Wide Open by\u00a0Sabrina\u00a0Carpenter",
    "header_image_thumbnail_url": "https://images.genius.com/bafc941dc36238932c84e7c7d51d2650.300x300x1.png",
    "header_image_url": "https://images.genius.com/bafc941dc36238932c84e7c7d51d2650.1000x1000x1.png",
    "id": 744882,
    "instrumental": false,
    "lyrics_owner_id": 104344,
    "lyrics_state": "complete",
    "lyrics_updated_at": 1723389502,
    "path": "/Sabrina-carpenter-eyes-wide-open-lyrics",
    "primary_artist_names": "Sabrina Carpenter",
    "pyongs_count": 201,
    "relationships_index_url": "https://genius.com/Sabrina-carpenter-eyes-wide-open-sample",
    "release_date_components": {
     "year": 2015,
     "month": 4,
     "day": 7
    },
    "release_date_for_display": "April 7, 2015",
    "release_date_with_abbreviated_month_for_display": "Apr. 7, 2015",
    "song_art_image_thumbnail_url": "https://images.genius.com/bafc941dc36238932c84e7c7d51d2650.300x300x1.png",
    "song_art_image_url": "https://images.genius.com/bafc941dc36238932c84e7c7d51d2650.1000x1000x1.png",
    "stats": {
     "unreviewed_annotations": 1,
     "hot": false,
     "pageviews": 38401
    },
    "title": "Eyes Wide Open",
    "title_with_featured": "Eyes Wide Open",
    "updated_by_human_at": 1723389502,
    "url": "https://genius.com/Sabrina-carpenter-eyes-wide-open-lyrics",
    "featured_artists": [],
    "primary_artist": {
     "_type": "artist",
     "api_path": "/artists/249592",
     "header_image_url": "https://images.genius.com/3d8df19075a7d820abc18af8b160de93.1000x333x1.jpg",
     "id": 249592,
     "image_url": "https://images.genius.com/ba5ff0975b4976a9351f3f26e66fa4b9.965x965x1.jpg",
     "index_character": "s",
     "is_meme_verified": false,
     "is_verified": true,
     "name": "Sabrina Carpenter",
     "slug": "Sabrina-carpenter",
     "url": "https://genius.com/artists/Sabrina-carpenter",
     "iq": 2353
    },
    "primary_artists": [
     {
      "_type": "artist",
      "api_path": "/artists/249592",
      "header_image_url": "https://images.genius.com/3d8df19075a7d820abc18af8b160de93.1000x333x1.jpg",
      "id": 249592,
      "image_url": "https://images.genius.com/ba5ff0975b4976a9351f3f26e66fa4b9.965x965x1.jpg",
      "index_character": "s",
      "is_meme_verified": false,
      "is_verified": true,
      "name": "Sabrina Carpenter",
      "slug": "Sabrina-carpenter",
      "url": "https://genius.com/artists/Sabrina-carpenter",
      "iq": 2353
     }
    ],
    "artist": "Sabrina Carpenter",
    "lyrics": "40 ContributorsEyes Wide Open Lyrics[Intro]\nLa-di-da-da-da-na\nYeah\n\n[Verse 1]\nEverybody loves to tell me\nI was born an old soul\nBetter keep my eyes wide open\nThere's so much that I don't know\nJust another hotel room\nNever felt so all alone\nI think about my granddad's eyes\nAnd they always send me home\nI can almost hear him now\nI gotta make him proud\n\n[Chorus]\nI keep my eyes wide open\nBless this ground, unbroken\nI'm about to make my way\nHeaven help me keep my faith\nAnd my eyes wide open\n\n[Verse 2]\nI can't see two steps ahead of me\nWhen the fog comes rollin' in\nI never thought I'd miss the rain\nLord knows how long it's been\nThis dream burns inside of me\nAnd I can't just let it go\nThere's still so much that I don't know\nSee Sabrina Carpenter LiveGet tickets as low as $29You might also like[Chorus]\nI keep my eyes wide open (No)\nBless this ground, unbroken\nI'm about to make my way\nHeaven help me keep my faith\nAnd my eyes wide open (Yeah)\n\n[Bridge]\nAll I have is just this moment\nI don't wanna miss a second\n'Cause it could all be gone in an instant\nYeah, in an instant\n\n[Chorus]\nI keep my eyes wide open (Open)\nBless this ground, unbroken (Yeah)\nI'm about to make my way (Make my way)\nHeaven help me keep my faith\nAnd my eyes wide open\n\n[Outro]\n(Keep my eyes wide open)\nI'm about to make my way\nHeaven help me keep my faith\n(Keep my eyes wide open)\nAnd my eyes wide open\nI keep my eyes wide open201Embed"
   }
  },
  {
   "number": 2,
   "song": {
    "_type": "song",
    "annotation_count": 1,
    "api_path": "/songs/556794",
    "artist_names": "Sabrina Carpenter",
    "full_title": "Can't Blame a Girl for Trying by\u00a0Sabrina\u00a0Carpenter",
    "header_image_thumbnail_url": "https://images.genius.com/bd93029fddf5a0bef36373730751cf73.300x300x1.png",
    "header_image_url": "https://images.genius.com/bd93029fddf5a0bef36373730751cf73.1000x1000x1.png",
    "id": 556794,
    "instrumental": false,
    "lyrics_owner_id": 971973,
    "lyrics_state": "complete",
    "lyrics_updated_at": 1723908707,
    "path": "/Sabrina-carpenter-cant-blame-a-girl-for-trying-lyrics",
    "primary_artist_names": "Sabrina Carpenter",
    "pyongs_count": 21,
    "relationships_index_url": "https://genius.com/Sabrina-carpenter-cant-blame-a-girl-for-trying-sample",
    "release_date_components": {
     "year": 2014,
     "month": 3,
     "day": 14
    },
    "release_date_for_display": "March 14, 2014",
    "release_date_with_abbreviated_month_for_display": "Mar. 14, 2014",
    "song_art_image_thumbnail_url": "https://images.genius.com/bd93029fddf5a0bef36373730751cf73.300x300x1.png",
    "song_art_image_url": "https://images.genius.com/bd93029fddf5a0bef36373730751cf73.1000x1000x1.png",
    "stats": {
     "unreviewed_annotations": 0,
     "concurrents": 2,
     "hot": false,
     "pageviews": 64479
    },
    "title": "Can\u2019t Blame a Girl for Trying",
    "title_with_featured": "Can't Blame a Girl for Trying",
    "updated_by_human_at": 1723908707,
    "url": "https://genius.com/Sabrina-carpenter-cant-blame-a-girl-for-trying-lyrics",
    "featured_artists": [],
    "primary_artist": {
     "_type": "artist",
     "api_path": "/artists/249592",
     "header_image_url": "https://images.genius.com/3d8df19075a7d820abc18af8b160de93.1000x333x1.jpg",
     "id": 249592,
     "image_url": "https://images.genius.com/ba5ff0975b4976a9351f3f26e66fa4b9.965x965x1.jpg",
     "index_character": "s",
     "is_meme_verified": false,
     "is_verified": true,
     "name": "Sabrina Carpenter",
     "slug": "Sabrina-carpenter",
     "url": "https://genius.com/artists/Sabrina-carpenter",
     "iq": 2353
    },
    "primary_artists": [
     {
      "_type": "artist",
      "api_path": "/artists/249592",
      "header_image_url": "https://images.genius.com/3d8df19075a7d820abc18af8b160de93.1000x333x1.jpg",
      "id": 249592,
      "image_url": "https://images.genius.com/ba5ff0975b4976a9351f3f26e66fa4b9.965x965x1.jpg",
      "index_character": "s",
      "is_meme_verified": false,
      "is_verified": true,
      "name": "Sabrina Carpenter",
      "slug": "Sabrina-carpenter",
      "url": "https://genius.com/artists/Sabrina-carpenter",
      "iq": 2353
     }
    ],
    "artist": "Sabrina Carpenter",
    "lyrics": "32 ContributorsTranslations\u0421\u0440\u043f\u0441\u043a\u0438Can\u2019t Blame a Girl for Trying Lyrics[Verse 1]\nHere I am again, the same old situation\nWhy does the guy thing have to be so complicated?\nI should've played it cool, instead, I made a fool\nOh, the things I do\n\n[Chorus]\n'Cause I'm young and I'm dumb\nI do stupid things when it comes to love\nAnd even if I always end up crying\nWell, you can't blame a girl for trying\nOh-oh-oh-oh, oh-oh-oh-oh\nNo, you can\u2019t blame a girl for trying\nUh-uh-uh-ooh, ooh-ooh-ooh-ooh-ooh\n\n[Verse 2]\nI should've shut my mouth, I could've kept it quiet\nI might have freaked him out 'cause I was so excited\nBut I just couldn't wait, I took a leap of faith\nOh, the things I say\n\n[Chorus]\n'Cause I'm young and I'm dumb\nI do stupid things when it comes to love\nAnd even if I always end up crying\nNo, you can't blame a girl for trying\nOh-oh-oh-oh, oh-oh-oh-oh\nNo, you can't blame a girl for trying\nOh-oh-oh-oh, no-oh-oh-oh, no\nSee Sabrina Carpenter LiveGet tickets as low as $29You might also like[Bridge]\nAnd I think sometimes\nI tend to be my own worst enemy\nAnd maybe someday\nI'm gonna catch a shooting star falling out of the blue\nDoing what I do\n\n[Verse 3]\nAnd just as I'm giving up, my heart is palpitating\nHere comes another one, it's so intoxicating\nBeing where I've been, I know that in the end\nI'll do it all again\n\n[Chorus]\n'Cause I'm young and I'm dumb\nI do stupid things when it comes to love\nAnd even if I always end up crying\nWell, love will find me, there ain't no denying\nThat you can't blame a girl for trying\nOh-oh-oh-oh, oh-oh-oh-oh\nNo, you can't blame a girl for trying\nMmm, uh-uh-uh-mmm-mmm21Embed"
   }
  },
  {
   "number": 3,
   "song": {
    "_type": "song",
    "annotation_count": 3,
    "api_path": "/songs/590020",
    "artist_names": "Sabrina Carpenter",
    "full_title": "The Middle of Starting Over by\u00a0Sabrina\u00a0Carpenter",
    "header_image_thumbnail_url": "https://images.genius.com/774d155f1affcdb96fab9a5a46459a6f.300x300x1.png",
    "header_image_url": "https://images.genius.com/774d155f1affcdb96fab9a5a46459a6f.1000x1000x1.png",
    "id": 590020,
    "instrumental": false,
    "lyrics_owner_id": 1304489,
    "lyrics_state": "complete",
    "lyrics_updated_at": 1703718916,
    "path": "/Sabrina-carpenter-the-middle-of-starting-over-lyrics",
    "primary_artist_names": "Sabrina Carpenter",
    "pyongs_count": 13,
    "relationships_index_url": "https://genius.com/Sabrina-carpenter-the-middle-of-starting-over-sample",
    "release_date_components": {
     "year": 2014,
     "month": 4,
     "day": 8
    },
    "release_date_for_display": "April 8, 2014",
    "release_date_with_abbreviated_month_for_display": "Apr. 8, 2014",
    "song_art_image_thumbnail_url": "https://images.genius.com/774d155f1affcdb96fab9a5a46459a6f.300x300x1.png",
    "song_art_image_url": "https://images.genius.com/774d155f1affcdb96fab9a5a46459a6f.1000x1000x1.png",
    "stats": {
     "unreviewed_annotations": 2,
     "hot": false,
     "pageviews": 20202
    },
    "title": "The Middle of Starting Over",
    "title_with_featured": "The Middle of Starting Over",
    "updated_by_human_at": 1718858492,
    "url": "https://genius.com/Sabrina-carpenter-the-middle-of-starting-over-lyrics",
    "featured_artists": [],
    "primary_artist": {
     "_type": "artist",
     "api_path": "/artists/249592",
     "header_image_url": "https://images.genius.com/3d8df19075a7d820abc18af8b160de93.1000x333x1.jpg",
     "id": 249592,
     "image_url": "https://images.genius.com/ba5ff0975b4976a9351f3f26e66fa4b9.965x965x1.jpg",
     "index_character": "s",
     "is_meme_verified": false,
     "is_verified": true,
     "name": "Sabrina Carpenter",
     "slug": "Sabrina-carpenter",
     "url": "https://genius.com/artists/Sabrina-carpenter",
     "iq": 2353
    },
    "primary_artists": [
     {
      "_type": "artist",
      "api_path": "/artists/249592",
      "header_image_url": "https://images.genius.com/3d8df19075a7d820abc18af8b160de93.1000x333x1.jpg",
      "id": 249592,
      "image_url": "https://images.genius.com/ba5ff0975b4976a9351f3f26e66fa4b9.965x965x1.jpg",
      "index_character": "s",
      "is_meme_verified": false,
      "is_verified": true,
      "name": "Sabrina Carpenter",
      "slug": "Sabrina-carpenter",
      "url": "https://genius.com/artists/Sabrina-carpenter",
      "iq": 2353
     }
    ],
    "artist": "Sabrina Carpenter",
    "lyrics": "25 ContributorsTranslations\u0421\u0440\u043f\u0441\u043a\u0438The Middle of Starting Over Lyrics[Refrain]\nOh, oh-oh-oh-oh\nOh-oh-oh-oh-oh\nOh-oh-oh-oh-oh-oh-oh\n\n[Verse 1]\nCast out to sea\nDrifting with the tide\nAnd no way of finding me\nNow that I'm free\nNothing but blue skies\nParadise in front of me\n\n[Pre-Chorus 1]\nAwake from this dream\nI hold my breath and just believe\n\n[Chorus]\nTired of all the troubles, they've been wasting my time\nI don't wanna fight, gonna leave it behind\nTake it on faith, now I'm ready to fly\nI'm in the middle of starting over\nBack to the beginning, gonna hit rewind\nChance to do it over, get it right this time\nLife gives you pennies, turn them into dimes\nI'm in the middle of starting over\nI'm in the middle of starting over\nSee Sabrina Carpenter LiveGet tickets as low as $29You might also like[Refrain]\nOh, oh-oh-oh-oh\nOh-oh-oh-oh-oh\nOh-oh-oh-oh-oh-oh-oh\n\n[Verse 2]\nAlone in a room\nTearing down the walls\nPainting over scars and bruises\nNow this is home\nFill it up with love\nAnd make the best of something new, yeah\n\n[Pre-Chorus 2]\nAs hard as it seems\nI hold my breath and just believe\n\n[Chorus]\nTired of all the troubles, they've been wasting my time\nI don't wanna fight, gonna leave it behind\nTake it on faith, now I'm ready to fly\nI'm in the middle of starting over\nBack to the beginning, gonna hit rewind\nChance to do it over, get it right this time\nLife gives you pennies, turn them into dimes\nI'm in the middle of starting over\n[Bridge]\nThe colors and the stars seem a little brighter (Oh-oh)\nTomorrow isn't far away (Not far away, oh-oh)\nThrough the hardest part\nI'm working towards a happy ending\n\n[Chorus]\nTired of all the troubles, they've been wasting my time\nI don't wanna fight, gonna leave it behind\nTake it on faith, now I'm ready to fly\nI'm in the middle of starting over\nBack to the beginning, gonna hit rewind\nChance to do it over, get it right this time\nLife gives you pennies, turn them into dimes\nI'm in the middle of starting over\nTired of all the troubles, they've been wasting my time (Oh, oh-oh-oh-oh)\nI don't wanna fight, gonna leave it behind (Oh-oh-oh-oh-oh)\nTake it on faith, now I'm ready to fly (Oh-oh-oh-oh-oh-oh-oh)\nI'm in the middle of starting over\nBack to the beginning, gonna hit rewind (Oh, oh-oh-oh-oh)\nChance to do it over, get it right this time (Oh-oh-oh-oh-oh)\nLife gives you pennies, turn them into dimes (Oh-oh-oh-oh-oh-oh-oh)\nI'm in the middle of starting over\nI'm in the middle of starting over\n\n[Refrain]\nOh, oh-oh-oh-oh\nOh-oh-oh-oh-oh\nOh-oh-oh-oh-oh-oh-oh13Embed"
   }
  },
  {
   "number": 4,
   "song": {
    "_type": "song",
    "annotation_count": 1,
    "api_path": "/songs/719477",
    "artist_names": "Sabrina Carpenter",
    "full_title": "We'll Be the Stars by\u00a0Sabrina\u00a0Carpenter",
    "header_image_thumbnail_url": "https://images.genius.com/6f2b7529559f140890db8d900c3f5a31.300x300x1.png",
    "header_image_url": "https://images.genius.com/6f2b7529559f140890db8d900c3f5a31.1000x1000x1.png",
    "id": 719477,
    "instrumental": false,
    "lyrics_owner_id": 1106295,
    "lyrics_state": "complete",
    "lyrics_updated_at": 1642630568,
    "path": "/Sabrina-carpenter-well-be-the-stars-lyrics",
    "primary_artist_names": "Sabrina Carpenter",
    "pyongs_count": 201,
    "relationships_index_url": "https://genius.com/Sabrina-carpenter-well-be-the-stars-sample",
    "release_date_components": {
     "year": 2015,
     "month": 1,
     "day": 13
    },
    "release_date_for_display": "January 13, 2015",
    "release_date_with_abbreviated_month_for_display": "Jan. 13, 2015",
    "song_art_image_thumbnail_url": "https://images.genius.com/6f2b7529559f140890db8d900c3f5a31.300x300x1.png",
    "song_art_image_url": "https://images.genius.com/6f2b7529559f140890db8d900c3f5a31.1000x1000x1.png",
    "stats": {
     "unreviewed_annotations": 0,
     "hot": false,
     "pageviews": 23124
    },
    "title": "We\u2019ll Be the Stars",
    "title_with_featured": "We'll Be the Stars",
    "updated_by_human_at": 1718858527,
    "url": "https://genius.com/Sabrina-carpenter-well-be-the-stars-lyrics",
    "featured_artists": [],
    "primary_artist": {
     "_type": "artist",
     "api_path": "/artists/249592",
     "header_image_url": "https://images.genius.com/3d8df19075a7d820abc18af8b160de93.1000x333x1.jpg",
     "id": 249592,
     "image_url": "https://images.genius.com/ba5ff0975b4976a9351f3f26e66fa4b9.965x965x1.jpg",
     "index_character": "s",
     "is_meme_verified": false,
     "is_verified": true,
     "name": "Sabrina Carpenter",
     "slug": "Sabrina-carpenter",
     "url": "https://genius.com/artists/Sabrina-carpenter",
     "iq": 2353
    },
    "primary_artists": [
     {
      "_type": "artist",
      "api_path": "/artists/249592",
      "header_image_url": "https://images.genius.com/3d8df19075a7d820abc18af8b160de93.1000x333x1.jpg",
      "id": 249592,
      "image_url": "https://images.genius.com/ba5ff0975b4976a9351f3f26e66fa4b9.965x965x1.jpg",
      "index_character": "s",
      "is_meme_verified": false,
      "is_verified": true,
      "name": "Sabrina Carpenter",
      "slug": "Sabrina-carpenter",
      "url": "https://genius.com/artists/Sabrina-carpenter",
      "iq": 2353
     }
    ],
    "artist": "Sabrina Carpenter",
    "lyrics": "29 ContributorsTranslations\u0421\u0440\u043f\u0441\u043a\u0438We\u2019ll Be the Stars Lyrics[Verse 1]\nWe are young, we are gold\nTrying things we didn't know\nLooking at the sky\nSee it come alive\nAll our fears became our hopes\nClimbed out every locked window\nWe rode a lion's mane\nAnd fell upon the rain\n\n[Pre-Chorus 1]\nWe can reach the constellations\nTrust me, all our dreams are breaking out\n\n[Chorus]\nNo, we're never gonna turn to dust\nYeah, all we really need is us\nDon't be scared to close your eyes\nNo, we're never gonna die\nWe'll be the stars, oh\nNo, we're never gonna step too far\nYeah, we're holding on to who we are\nWhen it's time to close your eyes\nThey will see us in the sky\nWe'll be the stars\nSee Sabrina Carpenter LiveGet tickets as low as $29You might also like[Post-Chorus]\nOh-oh-oh-oh, oh-oh-oh-oh\nWe'll be the stars\nOh-oh-oh-oh, oh-oh-oh-oh\nWe'll be the stars\n\n[Verse 2]\nLet me in\nHold me close\nFill my heart with simple notes\nSo when it's hard to see\nThey are there reminding me\nTake my breath\nAnd hold me high\nSo I can feel the city lights\nGlowing under me\nIt's in our reach\n\n[Pre-Chorus 2]\nWe're breaking out\n\n[Chorus]\nNo, we're never gonna turn to dust\nYeah, all we really need is us\nDon't be scared to close your eyes\nNo, we're never gonna die\nWe'll be the stars, oh\nNo, we're never gonna step too far\nYeah, we're holding on to who we are\nWhen it's time to close your eyes\nThey will see us in the sky\nWe'll be the stars\n[Post-Chorus]\nOh-oh-oh-oh, oh-oh-oh-oh\nWe'll be the stars\nOh-oh-oh-oh, oh-oh-oh-oh\nWe'll be the stars\n\n[Bridge]\nWe can reach the constellations\nTrust me, all our dreams are breaking out\n\n[Chorus]\nNo, we're never gonna turn to dust\nAll we really need is us\nWe'll be the stars, oh\nNo, we're never gonna step too far\nYeah, we're holding on to who we are\nWhen it's time to close your eyes\nThey will see us in the sky\nWe'll be the stars\n\n[Outro]\nOh-oh-oh-oh, oh-oh-oh-oh\nWe'll be the stars\nOh-oh-oh-oh, oh-oh-oh-oh\nWe'll be the stars\nOh-oh-oh-oh, oh-oh-oh-oh\nWe'll be the stars\nOh-oh-oh-oh, oh-oh-oh-oh\nWoah, we'll be the stars201Embed"
   }
  },
  {
   "number": 5,
   "song": {
    "_type": "song",
    "annotation_count": 2,
    "api_path": "/songs/1782514",
    "artist_names": "Sabrina Carpenter",
    "full_title": "Two Young Hearts by\u00a0Sabrina\u00a0Carpenter",
    "header_image_thumbnail_url": "https://images.genius.com/feca78e7614ab073a693106d2689112e.300x300x1.png",
    "header_image_url": "https://images.genius.com/feca78e7614ab073a693106d2689112e.1000x1000x1.png",
    "id": 1782514,
    "instrumental": false,
    "lyrics_owner_id": 1106295,
    "lyrics_state": "complete",
    "lyrics_updated_at": 1702575931,
    "path": "/Sabrina-carpenter-two-young-hearts-lyrics",
    "primary_artist_names": "Sabrina Carpenter",
    "pyongs_count": 4,
    "relationships_index_url": "https://genius.com/Sabrina-carpenter-two-young-hearts-sample",
    "release_date_components": {
     "year": 2015,
     "month": 4,
     "day": 14
    },
    "release_date_for_display": "April 14, 2015",
    "release_date_with_abbreviated_month_for_display": "Apr. 14, 2015",
    "song_art_image_thumbnail_url": "https://images.genius.com/feca78e7614ab073a693106d2689112e.300x300x1.png",
    "song_art_image_url": "https://images.genius.com/feca78e7614ab073a693106d2689112e.1000x1000x1.png",
    "stats": {
     "unreviewed_annotations": 1,
     "hot": false,
     "pageviews": 8207
    },
    "title": "Two Young Hearts",
    "title_with_featured": "Two Young Hearts",
    "updated_by_human_at": 1718854731,
    "url": "https://genius.com/Sabrina-carpenter-two-young-hearts-lyrics",
    "featured_artists": [],
    "primary_artist": {
     "_type": "artist",
     "api_path": "/artists/249592",
     "header_image_url": "https://images.genius.com/3d8df19075a7d820abc18af8b160de93.1000x333x1.jpg",
     "id": 249592,
     "image_url": "https://images.genius.com/ba5ff0975b4976a9351f3f26e66fa4b9.965x965x1.jpg",
     "index_character": "s",
     "is_meme_verified": false,
     "is_verified": true,
     "name": "Sabrina Carpenter",
     "slug": "Sabrina-carpenter",
     "url": "https://genius.com/artists/Sabrina-carpenter",
     "iq": 2353
    },
    "primary_artists": [
     {
      "_type": "artist",
      "api_path": "/artists/249592",
      "header_image_url": "https://images.genius.com/3d8df19075a7d820abc18af8b160de93.1000x333x1.jpg",
      "id": 249592,
      "image_url": "https://images.genius.com/ba5ff0975b4976a9351f3f26e66fa4b9.965x965x1.jpg",
      "index_character": "s",
      "is_meme_verified": false,
      "is_verified": true,
      "name": "Sabrina Carpenter",
      "slug": "Sabrina-carpenter",
      "url": "https://genius.com/artists/Sabrina-carpenter",
      "iq": 2353
     }
    ],
    "artist": "Sabrina Carpenter",
    "lyrics": "20 ContributorsTranslations\u0421\u0440\u043f\u0441\u043a\u0438Two Young Hearts Lyrics[Verse 1]\nIt's a narrow line I'm walking\nBetter watch my step\n'Cause we got everybody talking\nAnd I can hear 'em say\n\n[Pre-Chorus]\nMaybe in another lifetime\nMaybe when you're older\nWhat they don't know is\nI've already made up my mind (my mind)\nAnd yes, I know what love is\n\n[Chorus]\n'Cause we are two old souls\nWith two young hearts\nWe can run\nI will follow you to the end of the earth\nWhere we can see forever\nThey can never tear us apart\nTwo old souls\nWith two young hearts\nTwo young hearts\nThey say we're too young\n\n[Verse 2]\nI could lie awake in darkness\nOh, just to dream of you\nAnd you could lay your head on my chest\nYeah, just like you always do\nSee Sabrina Carpenter LiveGet tickets as low as $29You might also like[Pre-Chorus]\nMaybe in another lifetime\nMaybe when we're older\nAt least we know that\nWe've already made up our minds\nAnd yes, we know what love is\n\n[Chorus]\n'Cause we are two old souls\nWith two young hearts\nWe can run\nI will follow you to the end of the earth\nWhere we can see forever\nThey can never tear us apart\nTwo old souls\nWith two young hearts\nTwo young hearts, oh\n\n[Bridge]\nWe're gonna keep on running\nRunning for all that we are\nWe want it all or nothing\nWe knew it right from the start\nWe are a part of something\nSomething as old as time, time, time\n[Chorus]\n'Cause we are two old souls\nWith two young hearts\nWe can run\nI will follow you to the end of the earth\nWhere we can see forever\nThey can never tear us apart\nTwo old souls\nWith two young hearts\nTwo young hearts\n\n[Outro]\nYou're never too young4Embed"
   }
  },
  {
   "number": 6,
   "song": {
    "_type": "song",
    "annotation_count": 3,
    "api_path": "/songs/1782517",
    "artist_names": "Sabrina Carpenter",
    "full_title": "Your Love's Like by\u00a0Sabrina\u00a0Carpenter",
    "header_image_thumbnail_url": "https://images.genius.com/feca78e7614ab073a693106d2689112e.300x300x1.png",
    "header_image_url": "https://images.genius.com/feca78e7614ab073a693106d2689112e.1000x1000x1.png",
    "id": 1782517,
    "instrumental": false,
    "lyrics_owner_id": 1106295,
    "lyrics_state": "complete",
    "lyrics_updated_at": 1702576761,
    "path": "/Sabrina-carpenter-your-loves-like-lyrics",
    "primary_artist_names": "Sabrina Carpenter",
    "pyongs_count": 3,
    "relationships_index_url": "https://genius.com/Sabrina-carpenter-your-loves-like-sample",
    "release_date_components": {
     "year": 2015,
     "month": 4,
     "day": 14
    },
    "release_date_for_display": "April 14, 2015",
    "release_date_with_abbreviated_month_for_display": "Apr. 14, 2015",
    "song_art_image_thumbnail_url": "https://images.genius.com/feca78e7614ab073a693106d2689112e.300x300x1.png",
    "song_art_image_url": "https://images.genius.com/feca78e7614ab073a693106d2689112e.1000x1000x1.png",
    "stats": {
     "unreviewed_annotations": 1,
     "hot": false,
     "pageviews": 11500
    },
    "title": "Your Love\u2019s Like",
    "title_with_featured": "Your Love's Like",
    "updated_by_human_at": 1718855000,
    "url": "https://genius.com/Sabrina-carpenter-your-loves-like-lyrics",
    "featured_artists": [],
    "primary_artist": {
     "_type": "artist",
     "api_path": "/artists/249592",
     "header_image_url": "https://images.genius.com/3d8df19075a7d820abc18af8b160de93.1000x333x1.jpg",
     "id": 249592,
     "image_url": "https://images.genius.com/ba5ff0975b4976a9351f3f26e66fa4b9.965x965x1.jpg",
     "index_character": "s",
     "is_meme_verified": false,
     "is_verified": true,
     "name": "Sabrina Carpenter",
     "slug": "Sabrina-carpenter",
     "url": "https://genius.com/artists/Sabrina-carpenter",
     "iq": 2353
    },
    "primary_artists": [
     {
      "_type": "artist",
      "api_path": "/artists/249592",
      "header_image_url": "https://images.genius.com/3d8df19075a7d820abc18af8b160de93.1000x333x1.jpg",
      "id": 249592,
      "image_url": "https://images.genius.com/ba5ff0975b4976a9351f3f26e66fa4b9.965x965x1.jpg",
      "index_character": "s",
      "is_meme_verified": false,
      "is_verified": true,
      "name": "Sabrina Carpenter",
      "slug": "Sabrina-carpenter",
      "url": "https://genius.com/artists/Sabrina-carpenter",
      "iq": 2353
     }
    ],
    "artist": "Sabrina Carpenter",
    "lyrics": "20 ContributorsTranslations\u0421\u0440\u043f\u0441\u043a\u0438Your Love\u2019s Like Lyrics[Intro]\nOh-oh-oh, oh-oh-oh\n\n[Verse 1]\nSometimes life gets bitter\nI get strung out\nCaught in the middle\nAnd I can't breathe\nI just need a little taste of paradise\n\n[Pre-Chorus]\nI know a place I can escape to\nWhere I go\nTroubles never break through\nThe grass is greener\nMy head is clearer\nI got peace of mind when I fall into your eyes\n\n[Chorus]\nYour love's like breathing in the salty air\nOf summer on a private island just for me\nYour love's like the feeling I get\nWhen my favorite song's spinning in my head\nKeep it play-playing on repeat\nIt's like flowers in the spring time\nEvery day is Valentine's\nSo good it's hard to describe\nIt's like Paris after midnight\nDancing in the moonlight\nThat's what your love\nThat's what your love's like\nSee Sabrina Carpenter LiveGet tickets as low as $29You might also like[Post-Chorus]\n(Oh-oh-oh, oh-oh-oh)\nThat's what your love\nThat's what your love's like (Oh-oh-oh, oh-oh-oh)\nThat's what your love\nThat's what your love's like\n\n[Verse 2]\nStop signs\nI keep on running into\nRed lights\nMake me wanna scream like\nWhy can't it just be\nOnly you and me all the time\nIn a world no one can find\n\n[Chorus]\nYour love's like breathing in the salty air\nOf summer on a private island just for me\nYour love's like the feeling I get\nWhen my favorite song's spinning in my head\nKeep it play-playing on repeat\nIt's like flowers in the spring time\nEvery day is Valentine's\nSo good it's hard to describe\nIt's like Paris after midnight\nDancing in the moonlight\nThat's what your love\nThat's what your love's like\n[Post-Chorus]\n(Oh-oh-oh, oh-oh-oh)\nThat's what your love\nThat's what your love's like (Oh-oh-oh, oh-oh-oh)\nThat's what your love\nThat's what your love's like\n\n[Bridge]\nWhen life has left me numb\nAnd I need a pick me up\nThere's no better rush than your love\nYour love\nYour love\n\n[Chorus]\nYour love's like breathing in the salty air\nOf summer on a private island just for me\nYour love's like the feeling I get\nWhen my favorite song's spinning in my head\nKeep it play-playing on repeat\nIt's like walking on the ceiling\nCan't compare the feeling\nBetter than I could ever describe\nIt's like soaking in the sunrise\nNot a worry on my mind\nThat's what your love\nThat's what your love's like\n[Post-Chorus]\n(Oh-oh-oh, oh-oh-oh)\nThat's what your love\nThat's what your love's like (Oh-oh-oh, oh-oh-oh)\nThat's what your love\nThat's what your love's like (Oh-oh-oh, oh-oh-oh)\nThat's what your love\nThat's what your love's like (Oh-oh-oh, oh-oh-oh)\nThat's what your love's like3Embed"
   }
  },
  {
   "number": 7,
   "song": {
    "_type": "song",
    "annotation_count": 1,
    "api_path": "/songs/748018",
    "artist_names": "Sabrina Carpenter",
    "full_title": "Too Young by\u00a0Sabrina\u00a0Carpenter",
    "header_image_thumbnail_url": "https://images.genius.com/feca78e7614ab073a693106d2689112e.300x300x1.png",
    "header_image_url": "https://images.genius.com/feca78e7614ab073a693106d2689112e.1000x1000x1.png",
    "id": 748018,
    "instrumental": false,
    "lyrics_owner_id": 730074,
    "lyrics_state": "complete",
    "lyrics_updated_at": 1718421816,
    "path": "/Sabrina-carpenter-too-young-lyrics",
    "primary_artist_names": "Sabrina Carpenter",
    "pyongs_count": 8,
    "relationships_index_url": "https://genius.com/Sabrina-carpenter-too-young-sample",
    "release_date_components": {
     "year": 2015,
     "month": 4,
     "day": 14
    },
    "release_date_for_display": "April 14, 2015",
    "release_date_with_abbreviated_month_for_display": "Apr. 14, 2015",
    "song_art_image_thumbnail_url": "https://images.genius.com/feca78e7614ab073a693106d2689112e.300x300x1.png",
    "song_art_image_url": "https://images.genius.com/feca78e7614ab073a693106d2689112e.1000x1000x1.png",
    "stats": {
     "unreviewed_annotations": 0,
     "hot": false,
     "pageviews": 16066
    },
    "title": "Too Young",
    "title_with_featured": "Too Young",
    "updated_by_human_at": 1718855103,
    "url": "https://genius.com/Sabrina-carpenter-too-young-lyrics",
    "featured_artists": [],
    "primary_artist": {
     "_type": "artist",
     "api_path": "/artists/249592",
     "header_image_url": "https://images.genius.com/3d8df19075a7d820abc18af8b160de93.1000x333x1.jpg",
     "id": 249592,
     "image_url": "https://images.genius.com/ba5ff0975b4976a9351f3f26e66fa4b9.965x965x1.jpg",
     "index_character": "s",
     "is_meme_verified": false,
     "is_verified": true,
     "name": "Sabrina Carpenter",
     "slug": "Sabrina-carpenter",
     "url": "https://genius.com/artists/Sabrina-carpenter",
     "iq": 2353
    },
    "primary_artists": [
     {
      "_type": "artist",
      "api_path": "/artists/249592",
      "header_image_url": "https://images.genius.com/3d8df19075a7d820abc18af8b160de93.1000x333x1.jpg",
      "id": 249592,
      "image_url": "https://images.genius.com/ba5ff0975b4976a9351f3f26e66fa4b9.965x965x1.jpg",
      "index_character": "s",
      "is_meme_verified": false,
      "is_verified": true,
      "name": "Sabrina Carpenter",
      "slug": "Sabrina-carpenter",
      "url": "https://genius.com/artists/Sabrina-carpenter",
      "iq": 2353
     }
    ],
    "artist": "Sabrina Carpenter",
    "lyrics": "21 ContributorsTranslations\u0421\u0440\u043f\u0441\u043a\u0438Too Young Lyrics[Verse 1]\nBig lights\nPeople rushing to grow up, before you know\nStop signs\nDenied\nEveryone tells me I gotta go slow\n\n[Pre-Chorus]\nAnd it's gonna hurt sometimes\nNo matter what you do\nBut nothing can change my mind\n\n[Chorus]\nIf I'm too young to fall in love\nWhy do you keep runnin' through my brain?\nIf I'm too young to know anything\nThen why do I know that I'm just not the same?\nDon't tell me I won't\nDon't tell me I can't feel\nWhat I'm feeling is real\n'Cause I'm not too young\n\n[Verse 2]\nRain drops\nDeep thoughts\nPictures of you and me wherever I go\nLaughing\nRunning to a place where nobody says \"no\"\nSee Sabrina Carpenter LiveGet tickets as low as $29You might also like[Pre-Chorus]\nAnd it's gonna hurt sometimes\nNo matter what you do\nBut I've got to fall to fly, yeah\n\n[Chorus]\nIf I'm too young to fall in love\nWhy do you keep runnin' through my brain?\nIf I'm too young to know anything\nThen why do I know that I'm just not the same?\nDon't tell me I won't\nDon't tell me I can't feel\nWhat I'm feeling is real\n'Cause I'm not too young\n\n[Interlude]\n'Cause I'm not too young, oh\nYeah, yeah, yeah\n\n[Chorus]\nAnd if I'm too young to fall in love\nWhy do you keep runnin' through my brain?\nAnd if I'm too young to know anything\nThen why do I know that I'm just not the same?\nDon't tell me I won't\nDon't tell me I can't feel\nWhat I'm feeling is real\n'Cause I'm not too young\n'Cause I'm not too young, no\n'Cause I'm not too young8Embed"
   }
  },
  {
   "number": 8,
   "song": {
    "_type": "song",
    "annotation_count": 3,
    "api_path": "/songs/1782521",
    "artist_names": "Sabrina Carpenter",
    "full_title": "Seamless by\u00a0Sabrina\u00a0Carpenter",
    "header_image_thumbnail_url": "https://images.genius.com/feca78e7614ab073a693106d2689112e.300x300x1.png",
    "header_image_url": "https://images.genius.com/feca78e7614ab073a693106d2689112e.1000x1000x1.png",
    "id": 1782521,
    "instrumental": false,
    "lyrics_owner_id": 1106295,
    "lyrics_state": "complete",
    "lyrics_updated_at": 1522640542,
    "path": "/Sabrina-carpenter-seamless-lyrics",
    "primary_artist_names": "Sabrina Carpenter",
    "pyongs_count": 1,
    "relationships_index_url": "https://genius.com/Sabrina-carpenter-seamless-sample",
    "release_date_components": {
     "year": 2015,
     "month": 4,
     "day": 14
    },
    "release_date_for_display": "April 14, 2015",
    "release_date_with_abbreviated_month_for_display": "Apr. 14, 2015",
    "song_art_image_thumbnail_url": "https://images.genius.com/feca78e7614ab073a693106d2689112e.300x300x1.png",
    "song_art_image_url": "https://images.genius.com/feca78e7614ab073a693106d2689112e.1000x1000x1.png",
    "stats": {
     "unreviewed_annotations": 1,
     "hot": false,
     "pageviews": 17863
    },
    "title": "Seamless",
    "title_with_featured": "Seamless",
    "updated_by_human_at": 1718855562,
    "url": "https://genius.com/Sabrina-carpenter-seamless-lyrics",
    "featured_artists": [],
    "primary_artist": {
     "_type": "artist",
     "api_path": "/artists/249592",
     "header_image_url": "https://images.genius.com/3d8df19075a7d820abc18af8b160de93.1000x333x1.jpg",
     "id": 249592,
     "image_url": "https://images.genius.com/ba5ff0975b4976a9351f3f26e66fa4b9.965x965x1.jpg",
     "index_character": "s",
     "is_meme_verified": false,
     "is_verified": true,
     "name": "Sabrina Carpenter",
     "slug": "Sabrina-carpenter",
     "url": "https://genius.com/artists/Sabrina-carpenter",
     "iq": 2353
    },
    "primary_artists": [
     {
      "_type": "artist",
      "api_path": "/artists/249592",
      "header_image_url": "https://images.genius.com/3d8df19075a7d820abc18af8b160de93.1000x333x1.jpg",
      "id": 249592,
      "image_url": "https://images.genius.com/ba5ff0975b4976a9351f3f26e66fa4b9.965x965x1.jpg",
      "index_character": "s",
      "is_meme_verified": false,
      "is_verified": true,
      "name": "Sabrina Carpenter",
      "slug": "Sabrina-carpenter",
      "url": "https://genius.com/artists/Sabrina-carpenter",
      "iq": 2353
     }
    ],
    "artist": "Sabrina Carpenter",
    "lyrics": "17 ContributorsTranslations\u0421\u0440\u043f\u0441\u043a\u0438Seamless Lyrics[Verse 1]\nGood morning, you're leaving\nI'll see you in the evening\nMy best friend 'til the end\nMy better half, no pretend\nOur language is sacred\nThough people try to solve it\nNew adventures on the way\n\n[Chorus]\nYou and me together\nTake on the world forever\nI know all your secrets\nAnd I promise you, I'm gonna keep them\nI'll be there when you are feeling clueless\nYou and me, oh yeah, we're seamless\nWhoa-oh-oh-oh-oh, yeah\nWhoa-oh-oh-oh-oh-oh\n\n[Verse 2]\nWe're klutzy, but so lucky\nThat I always have you to catch me\nWe're partners in crime\nYou're stuck with me your whole life\nSo different\nOut of our minds\nFrom a planet that's hard to find\nEvery second every day\nSee Sabrina Carpenter LiveGet tickets as low as $29You might also like[Chorus]\nYou and me together\nTake on the world forever\nI know all your secrets\nAnd I promise you, I'm gonna keep them\nI'll be there when you are feeling clueless\nYou and me, oh yeah, we're seamless\n\n[Bridge]\nYou're right by my side whenever I need you\nThrough the hardest times, I'll be there for you\nAt the crack of dawn when the moon is gone\nI won't be hard to find\n'Cause you and me, oh yeah, we're seamless\nWhoa-oh-oh-oh-oh, hey\nOh-oh-oh-oh, oh yeah\n\n[Chorus]\nYou and me together\nTake on the world forever\nI know all your secrets\nAnd I promise you, I'm gonna keep them\nI'll be there when you are feeling clueless\nYou and me, oh yeah, we're seamless\nWhoa-oh-oh-oh-oh, hey\nWhoa-oh-oh-oh-oh-oh-oh1Embed"
   }
  },
  {
   "number": 9,
   "song": {
    "_type": "song",
    "annotation_count": 2,
    "api_path": "/songs/1782524",
    "artist_names": "Sabrina Carpenter",
    "full_title": "Right Now by\u00a0Sabrina\u00a0Carpenter",
    "header_image_thumbnail_url": "https://images.genius.com/feca78e7614ab073a693106d2689112e.300x300x1.png",
    "header_image_url": "https://images.genius.com/feca78e7614ab073a693106d2689112e.1000x1000x1.png",
    "id": 1782524,
    "instrumental": false,
    "lyrics_owner_id": 1106295,
    "lyrics_state": "complete",
    "lyrics_updated_at": 1614581894,
    "path": "/Sabrina-carpenter-right-now-lyrics",
    "primary_artist_names": "Sabrina Carpenter",
    "pyongs_count": null,
    "relationships_index_url": "https://genius.com/Sabrina-carpenter-right-now-sample",
    "release_date_components": {
     "year": 2015,
     "month": 4,
     "day": 14
    },
    "release_date_for_display": "April 14, 2015",
    "release_date_with_abbreviated_month_for_display": "Apr. 14, 2015",
    "song_art_image_thumbnail_url": "https://images.genius.com/feca78e7614ab073a693106d2689112e.300x300x1.png",
    "song_art_image_url": "https://images.genius.com/feca78e7614ab073a693106d2689112e.1000x1000x1.png",
    "stats": {
     "unreviewed_annotations": 1,
     "hot": false,
     "pageviews": 8020
    },
    "title": "Right Now",
    "title_with_featured": "Right Now",
    "updated_by_human_at": 1718855530,
    "url": "https://genius.com/Sabrina-carpenter-right-now-lyrics",
    "featured_artists": [],
    "primary_artist": {
     "_type": "artist",
     "api_path": "/artists/249592",
     "header_image_url": "https://images.genius.com/3d8df19075a7d820abc18af8b160de93.1000x333x1.jpg",
     "id": 249592,
     "image_url": "https://images.genius.com/ba5ff0975b4976a9351f3f26e66fa4b9.965x965x1.jpg",
     "index_character": "s",
     "is_meme_verified": false,
     "is_verified": true,
     "name": "Sabrina Carpenter",
     "slug": "Sabrina-carpenter",
     "url": "https://genius.com/artists/Sabrina-carpenter",
     "iq": 2353
    },
    "primary_artists": [
     {
      "_type": "artist",
      "api_path": "/artists/249592",
      "header_image_url": "https://images.genius.com/3d8df19075a7d820abc18af8b160de93.1000x333x1.jpg",
      "id": 249592,
      "image_url": "https://images.genius.com/ba5ff0975b4976a9351f3f26e66fa4b9.965x965x1.jpg",
      "index_character": "s",
      "is_meme_verified": false,
      "is_verified": true,
      "name": "Sabrina Carpenter",
      "slug": "Sabrina-carpenter",
      "url": "https://genius.com/artists/Sabrina-carpenter",
      "iq": 2353
     }
    ],
    "artist": "Sabrina Carpenter",
    "lyrics": "16 ContributorsTranslations\u0421\u0440\u043f\u0441\u043a\u0438Right Now Lyrics[Verse 1]\nWe'll never be as young as we are right now\nWe'll never see the world like we do right now\nSo take in what's around you\nPut your camera down\nTake a shot\nGive it all you got\nI have a way of getting stuck on yesterday\nI tend to miss the little things that come my way\nAlways looking forward\nAlways looking back\nThey seem so near\nBut they're not here\n\n[Pre-Chorus]\n'Cause time moves on so quickly\nWithout or with me\nI've got to take a breath\n\n[Chorus]\nAnd slow down, slow down\nMy mind is racing\nCatch up, catch up\nI've gotta pace myself\nI'm always wondering\nBut I don't need to go right now\nLet go, let go (let go)\nWe hold our fears too tight\nBegin, begin (begin)\nTo live your life\nThe present is our future past\nWe've gotta make this moment last\nRight now\nSee Sabrina Carpenter LiveGet tickets as low as $29You might also like[Verse 2]\nHave you ever noticed how your heartbeat feels\nWhen your love is so excited?\n'Cause it's getting real\nHave you stopped to listen\nTo what's in your soul?\nThat's your intuition\nAnd it always knows\n\n[Pre-Chorus]\nTime moves on so quickly\nWithout or with me\nI've got to take a breath\n\n[Chorus]\nAnd slow down, slow down\nMy mind is racing\nCatch up, catch up\nI've gotta pace myself\nI'm always wondering\nBut I don't need to go right now\nLet go, let go (let go)\nWe hold our fears too tight\nBegin, begin (begin)\nTo live your life\nThe present is our future past\nWe've gotta make this moment last\nRight now\n[Breakdown]\nOh, right now (Right now)\nRight now (Right now)\nEnjoy the ride\nThe ride that you're on\nRight now\nRight now\nYeah\n\n[Outro]\nLet go, let go\nWe hold our fears too tight\nBegin, begin\nTo live your life\nThe present is our future past\nWe've gotta make this moment last\nRight nowEmbed"
   }
  },
  {
   "number": 10,
   "song": {
    "_type": "song",
    "annotation_count": 1,
    "api_path": "/songs/973852",
    "artist_names": "Sabrina Carpenter",
    "full_title": "Darling I'm a Mess by\u00a0Sabrina\u00a0Carpenter",
    "header_image_thumbnail_url": "https://images.genius.com/feca78e7614ab073a693106d2689112e.300x300x1.png",
    "header_image_url": "https://images.genius.com/feca78e7614ab073a693106d2689112e.1000x1000x1.png",
    "id": 973852,
    "instrumental": false,
    "lyrics_owner_id": 305161,
    "lyrics_state": "complete",
    "lyrics_updated_at": 1719677926,
    "path": "/Sabrina-carpenter-darling-im-a-mess-lyrics",
    "primary_artist_names": "Sabrina Carpenter",
    "pyongs_count": 3,
    "relationships_index_url": "https://genius.com/Sabrina-carpenter-darling-im-a-mess-sample",
    "release_date_components": {
     "year": 2015,
     "month": 4,
     "day": 14
    },
    "release_date_for_display": "April 14, 2015",
    "release_date_with_abbreviated_month_for_display": "Apr. 14, 2015",
    "song_art_image_thumbnail_url": "https://images.genius.com/feca78e7614ab073a693106d2689112e.300x300x1.png",
    "song_art_image_url": "https://images.genius.com/feca78e7614ab073a693106d2689112e.1000x1000x1.png",
    "stats": {
     "unreviewed_annotations": 0,
     "hot": false,
     "pageviews": 7858
    },
    "title": "Darling I\u2019m a Mess",
    "title_with_featured": "Darling I'm a Mess",
    "updated_by_human_at": 1719677926,
    "url": "https://genius.com/Sabrina-carpenter-darling-im-a-mess-lyrics",
    "featured_artists": [],
    "primary_artist": {
     "_type": "artist",
     "api_path": "/artists/249592",
     "header_image_url": "https://images.genius.com/3d8df19075a7d820abc18af8b160de93.1000x333x1.jpg",
     "id": 249592,
     "image_url": "https://images.genius.com/ba5ff0975b4976a9351f3f26e66fa4b9.965x965x1.jpg",
     "index_character": "s",
     "is_meme_verified": false,
     "is_verified": true,
     "name": "Sabrina Carpenter",
     "slug": "Sabrina-carpenter",
     "url": "https://genius.com/artists/Sabrina-carpenter",
     "iq": 2353
    },
    "primary_artists": [
     {
      "_type": "artist",
      "api_path": "/artists/249592",
      "header_image_url": "https://images.genius.com/3d8df19075a7d820abc18af8b160de93.1000x333x1.jpg",
      "id": 249592,
      "image_url": "https://images.genius.com/ba5ff0975b4976a9351f3f26e66fa4b9.965x965x1.jpg",
      "index_character": "s",
      "is_meme_verified": false,
      "is_verified": true,
      "name": "Sabrina Carpenter",
      "slug": "Sabrina-carpenter",
      "url": "https://genius.com/artists/Sabrina-carpenter",
      "iq": 2353
     }
    ],
    "artist": "Sabrina Carpenter",
    "lyrics": "17 ContributorsTranslations\u0421\u0440\u043f\u0441\u043a\u0438Darling I\u2019m a Mess Lyrics[Verse 1]\nThis might be wrong, but he's all I know\nHe's all I know\nMost times, I pretend that he's just a friend\nHe's just a friend\n\n[Pre-Chorus]\nYeah, I'll try to make our hearts beat in time\nEven though your rhythm might not beat with mine\n\n[Chorus]\nBut darling, I'm a mess without your love\nHeaven knows I'm trying, I'm trying to get by\nBut darling, I'm a mess without your love\nAll I need is one more goodbye kiss\n\n[Verse 2]\nYour lips I'll miss 'cause they're all I know\nI can't let you go\nAnd I won't forget all that you said\nIt's engraved in my head\n\n[Pre-Chorus]\nYeah, I'll try to make our hearts beat in time\nEven though your rhythm might not beat with mine\nSee Sabrina Carpenter LiveGet tickets as low as $29You might also like[Chorus]\nBut darling, I'm a mess without your love\nHeaven knows I'm trying, I'm trying to get by\nBut darling, I'm a mess without your love\nAll I need is one more goodbye kiss\nNo, oh, a goodbye kiss\n\n[Bridge]\nYeah, I'll try to make our hearts beat in time\nEven though your rhythm might not beat with mine\n\n[Chorus]\nBut darling, I'm a mess without your love (Without your love)\nHeaven knows I'm trying, I'm trying to get by (No, no, no, no, no)\nBut darling, I'm a mess without your love\nAll I need is one more goodbye kiss (One more goodbye)3Embed"
   }
  },
  {
   "number": 11,
   "song": {
    "_type": "song",
    "annotation_count": 1,
    "api_path": "/songs/719472",
    "artist_names": "Sabrina Carpenter",
    "full_title": "White Flag by\u00a0Sabrina\u00a0Carpenter",
    "header_image_thumbnail_url": "https://images.genius.com/feca78e7614ab073a693106d2689112e.300x300x1.png",
    "header_image_url": "https://images.genius.com/feca78e7614ab073a693106d2689112e.1000x1000x1.png",
    "id": 719472,
    "instrumental": false,
    "lyrics_owner_id": 1106295,
    "lyrics_state": "complete",
    "lyrics_updated_at": 1666130439,
    "path": "/Sabrina-carpenter-white-flag-lyrics",
    "primary_artist_names": "Sabrina Carpenter",
    "pyongs_count": 1,
    "relationships_index_url": "https://genius.com/Sabrina-carpenter-white-flag-sample",
    "release_date_components": {
     "year": 2014,
     "month": 4,
     "day": 8
    },
    "release_date_for_display": "April 8, 2014",
    "release_date_with_abbreviated_month_for_display": "Apr. 8, 2014",
    "song_art_image_thumbnail_url": "https://images.genius.com/feca78e7614ab073a693106d2689112e.300x300x1.png",
    "song_art_image_url": "https://images.genius.com/feca78e7614ab073a693106d2689112e.1000x1000x1.png",
    "stats": {
     "unreviewed_annotations": 1,
     "hot": false,
     "pageviews": 9437
    },
    "title": "White Flag",
    "title_with_featured": "White Flag",
    "updated_by_human_at": 1718855680,
    "url": "https://genius.com/Sabrina-carpenter-white-flag-lyrics",
    "featured_artists": [],
    "primary_artist": {
     "_type": "artist",
     "api_path": "/artists/249592",
     "header_image_url": "https://images.genius.com/3d8df19075a7d820abc18af8b160de93.1000x333x1.jpg",
     "id": 249592,
     "image_url": "https://images.genius.com/ba5ff0975b4976a9351f3f26e66fa4b9.965x965x1.jpg",
     "index_character": "s",
     "is_meme_verified": false,
     "is_verified": true,
     "name": "Sabrina Carpenter",
     "slug": "Sabrina-carpenter",
     "url": "https://genius.com/artists/Sabrina-carpenter",
     "iq": 2353
    },
    "primary_artists": [
     {
      "_type": "artist",
      "api_path": "/artists/249592",
      "header_image_url": "https://images.genius.com/3d8df19075a7d820abc18af8b160de93.1000x333x1.jpg",
      "id": 249592,
      "image_url": "https://images.genius.com/ba5ff0975b4976a9351f3f26e66fa4b9.965x965x1.jpg",
      "index_character": "s",
      "is_meme_verified": false,
      "is_verified": true,
      "name": "Sabrina Carpenter",
      "slug": "Sabrina-carpenter",
      "url": "https://genius.com/artists/Sabrina-carpenter",
      "iq": 2353
     }
    ],
    "artist": "Sabrina Carpenter",
    "lyrics": "25 ContributorsTranslations\u0421\u0440\u043f\u0441\u043a\u0438White Flag Lyrics[Verse 1]\nTake, take it all away\nSave my heart for another day\nI'm up late on the telephone\nAnd I'm all alone with the dial tone\nWait, wait 'til the sun is up\nDrown my dreams in a coffee cup\nPalms out, wanna beg for luck\nBut I'm way too proud\nNever giving up\n\n[Chorus]\nOh, something's gotta happen\nSomething's gotta give\nAnd something's got to break\nI know someday it's gonna happen\nSomeday it's gonna give\nCan't always be this way\nAnd if the riptide comes to get me\nAnd pulls me under\nIt won't upset me\nI'll go down\n(Oh, oh, oh, oh, oh, oh)\nI'll throw the white flag of surrender\nKnock me down\nNot forever\nJust for now\n(Oh, oh, oh, oh, oh, oh)\nSee Sabrina Carpenter LiveGet tickets as low as $29You might also like[Verse 2]\nGive, give everything I've got\nOut of reach, but I'll take a shot\nKick rocks in the parking lot\nFeel like giving up\nBut I'll never stop\nRun, run, running like a fool\nNever win if you never lose\nFind hope and a little truth\nGonna learn new tricks\nGotta jump through hoops\n\n[Chorus]\nOh, something's gotta happen\nSomething's gotta give\nAnd something's got to break\nI know someday it's gonna happen\nSomeday it's gonna give\nCan't always be this way\nAnd if the riptide comes to get me\nAnd pulls me under\nIt won't upset me\nI'll go down\n(Oh, oh, oh, oh, oh, oh)\nI'll throw the white flag of surrender\nKnock me down\nNot forever\nJust for now\n(Oh, oh, oh, oh, oh, oh)\n[Bridge]\nNot forever, just for now\nNot forever, just for now\nNot forever, not forever, not forever\nWon't stay down\nNot forever, just for now\nNot forever, just for now\nNot forever, not forever, not forever\nWon't stay down\n\n[Chorus]\nAnd if the riptide comes to get me\nAnd pulls me under\nIt won't upset me\nAnd if the riptide comes to get me\nAnd pulls me under\nIt won't upset me\nI'll go down\n(Oh oh oh oh oh oh)\nI'll throw the white flag of surrender\nKnock me down\nNot forever\nJust for now\n(Oh, oh, oh, oh, oh, oh)\n\n[Repeat]\nAnd if the riptide comes to get me\nAnd pulls me under\nIt won't upset me\nAnd if the riptide comes to get me\nAnd pulls me under\nIt won't upset me\nI'll go down\n(Oh oh oh oh oh oh)\nI'll throw the white flag of surrender\nKnock me down\nNot forever\nJust for now\n(Oh, oh, oh, oh, oh, oh)1Embed"
   }
  },
  {
   "number": 12,
   "song": {
    "_type": "song",
    "annotation_count": 0,
    "api_path": "/songs/719475",
    "artist_names": "Sabrina Carpenter",
    "full_title": "Best Thing I Got by\u00a0Sabrina\u00a0Carpenter",
    "header_image_thumbnail_url": "https://images.genius.com/feca78e7614ab073a693106d2689112e.300x300x1.png",
    "header_image_url": "https://images.genius.com/feca78e7614ab073a693106d2689112e.1000x1000x1.png",
    "id": 719475,
    "instrumental": false,
    "lyrics_owner_id": 1106295,
    "lyrics_state": "complete",
    "lyrics_updated_at": 1611339100,
    "path": "/Sabrina-carpenter-best-thing-i-got-lyrics",
    "primary_artist_names": "Sabrina Carpenter",
    "pyongs_count": 4,
    "relationships_index_url": "https://genius.com/Sabrina-carpenter-best-thing-i-got-sample",
    "release_date_components": {
     "year": 2014,
     "month": 4,
     "day": 8
    },
    "release_date_for_display": "April 8, 2014",
    "release_date_with_abbreviated_month_for_display": "Apr. 8, 2014",
    "song_art_image_thumbnail_url": "https://images.genius.com/feca78e7614ab073a693106d2689112e.300x300x1.png",
    "song_art_image_url": "https://images.genius.com/feca78e7614ab073a693106d2689112e.1000x1000x1.png",
    "stats": {
     "unreviewed_annotations": 0,
     "hot": false,
     "pageviews": 7578
    },
    "title": "Best Thing I Got",
    "title_with_featured": "Best Thing I Got",
    "updated_by_human_at": 1718855859,
    "url": "https://genius.com/Sabrina-carpenter-best-thing-i-got-lyrics",
    "featured_artists": [],
    "primary_artist": {
     "_type": "artist",
     "api_path": "/artists/249592",
     "header_image_url": "https://images.genius.com/3d8df19075a7d820abc18af8b160de93.1000x333x1.jpg",
     "id": 249592,
     "image_url": "https://images.genius.com/ba5ff0975b4976a9351f3f26e66fa4b9.965x965x1.jpg",
     "index_character": "s",
     "is_meme_verified": false,
     "is_verified": true,
     "name": "Sabrina Carpenter",
     "slug": "Sabrina-carpenter",
     "url": "https://genius.com/artists/Sabrina-carpenter",
     "iq": 2353
    },
    "primary_artists": [
     {
      "_type": "artist",
      "api_path": "/artists/249592",
      "header_image_url": "https://images.genius.com/3d8df19075a7d820abc18af8b160de93.1000x333x1.jpg",
      "id": 249592,
      "image_url": "https://images.genius.com/ba5ff0975b4976a9351f3f26e66fa4b9.965x965x1.jpg",
      "index_character": "s",
      "is_meme_verified": false,
      "is_verified": true,
      "name": "Sabrina Carpenter",
      "slug": "Sabrina-carpenter",
      "url": "https://genius.com/artists/Sabrina-carpenter",
      "iq": 2353
     }
    ],
    "artist": "Sabrina Carpenter",
    "lyrics": "17 ContributorsTranslations\u0421\u0440\u043f\u0441\u043a\u0438Best Thing I Got Lyrics[Verse 1]\nSo what if I just wanna be\nA little bit out of my mind?\nI let you take my heart and I like it\nSo what if I happen to be\nA little bit out of my mind?\nI bet I'll steal your heart and you'll like it\n\n[Pre-Chorus]\nAnd I don't think it's any kind of secret\nI feel you from a million miles away\n\n[Chorus]\nAnd your love is the best thing that I got\nAnd it's only just begun\nBut it's never gonna stop\nIt's the best thing\nThe best thing that I got\n\n[Verse 2]\nI know sometimes it seems like I\nI'm just a little bit behind\nI get back on the beat and you know it\nAnd sometimes I can tell that I\nI'm just a little out of time\nI make you skip a beat and I know it\nSee Sabrina Carpenter LiveGet tickets as low as $29You might also like[Pre-Chorus]\nBut I don't think it's any kind of secret\nI think of you a billion times a day\n\n[Chorus]\nYour love is the best thing that I got\nAnd it's only just begun\nBut it's never gonna stop\nIt's the best thing\nThe best thing that I got\n\n[Bridge]\nSo don't feel lonely tonight\nYou know I'll never be hard to find\nSo don't go out of your mind (Out of your mind)\nYou know I'll never be too hard to find\n\n[Breakdown]\nI know sometimes it seems like I\nI'm just a little bit behind\nI get back on the beat and you know it\n\n[Chorus]\nYour love is the best thing that I got\nAnd it's only just begun\nBut it's never gonna stop\nIt's the best thing\nThe best thing that I got\n[Outro]\nYour love is the best thing\nAnd it's only just begun\nIt's the best thing4Embed"
   }
  }
 ]
}